deepchem/__init__.py
deepchem/data/__init__.py
deepchem/data/data_loader.py
deepchem/data/datasets.py
deepchem/data/pytorch_datasets.py
deepchem/data/supports.py
deepchem/dock/__init__.py
deepchem/dock/binding_pocket.py
deepchem/dock/docking.py
deepchem/dock/pose_generation.py
deepchem/dock/pose_scoring.py
deepchem/feat/__init__.py
deepchem/feat/atomic_conformation.py
deepchem/feat/base_classes.py
deepchem/feat/bert_tokenizer.py
deepchem/feat/binding_pocket_features.py
deepchem/feat/bio_seq_featurizer.py
deepchem/feat/deepvariant_featurizer.py
deepchem/feat/deepvariant_pileup_featurizer.py
deepchem/feat/dft_data.py
deepchem/feat/graph_data.py
deepchem/feat/graph_features.py
deepchem/feat/huggingface_featurizer.py
deepchem/feat/mol_graphs.py
deepchem/feat/reaction_featurizer.py
deepchem/feat/roberta_tokenizer.py
deepchem/feat/smiles_tokenizer.py
deepchem/feat/complex_featurizers/__init__.py
deepchem/feat/complex_featurizers/complex_atomic_coordinates.py
deepchem/feat/complex_featurizers/contact_fingerprints.py
deepchem/feat/complex_featurizers/grid_featurizers.py
deepchem/feat/complex_featurizers/rdkit_grid_featurizer.py
deepchem/feat/complex_featurizers/splif_fingerprints.py
deepchem/feat/material_featurizers/__init__.py
deepchem/feat/material_featurizers/cgcnn_featurizer.py
deepchem/feat/material_featurizers/element_property_fingerprint.py
deepchem/feat/material_featurizers/elemnet_featurizer.py
deepchem/feat/material_featurizers/lcnn_featurizer.py
deepchem/feat/material_featurizers/sine_coulomb_matrix.py
deepchem/feat/molecule_featurizers/__init__.py
deepchem/feat/molecule_featurizers/atomic_coordinates.py
deepchem/feat/molecule_featurizers/bp_symmetry_function_input.py
deepchem/feat/molecule_featurizers/circular_fingerprint.py
deepchem/feat/molecule_featurizers/conformer_featurizer.py
deepchem/feat/molecule_featurizers/coulomb_matrices.py
deepchem/feat/molecule_featurizers/dmpnn_featurizer.py
deepchem/feat/molecule_featurizers/equivariant_graph_featurizer.py
deepchem_su-2.8.1.dev20250402122923.dist-info/METADATA
deepchem_su-2.8.1.dev20250402122923.dist-info/WHEEL
deepchem_su-2.8.1.dev20250402122923.dist-info/top_level.txt
deepchem_su-2.8.1.dev20250402122923.dist-info/RECORD
